flake8_allure_tree/__init__.py
flake8_allure_tree/flake8_allure.py
flake8_allure_tree-1.0.1.dist-info/METADATA
flake8_allure_tree-1.0.1.dist-info/WHEEL
flake8_allure_tree-1.0.1.dist-info/entry_points.txt
flake8_allure_tree-1.0.1.dist-info/top_level.txt
flake8_allure_tree-1.0.1.dist-info/RECORD
