Metadata-Version: 2.1
Name: flake8-allure-tree
Version: 1.0.1
Summary: Flake8 plugin to check allure decorators on test classes and methods
Author: Petr Alekseev
Author-email: petrmissial@gmail.com
License: MIT license
Keywords: flake8,pytest,py.test,allure
Classifier: Framework :: Pytest
Classifier: Development Status :: 2 - Pre-Alpha
Classifier: Intended Audience :: Developers
Classifier: License :: OSI Approved :: MIT License
Classifier: Natural Language :: English
Classifier: Programming Language :: Python :: 2
Classifier: Programming Language :: Python :: 2.7
Classifier: Programming Language :: Python :: 3
Classifier: Programming Language :: Python :: 3.4
Classifier: Programming Language :: Python :: 3.5
Classifier: Programming Language :: Python :: 3.6
Classifier: Programming Language :: Python :: 3.7
Classifier: Programming Language :: Python :: 3.8
Classifier: Programming Language :: Python :: 3.9
Requires-Dist: pytest
Requires-Dist: flake8-plugin-utils
